hydrilla/__init__.py
hydrilla/builder/__init__.py
hydrilla/builder/__main__.py
hydrilla/builder/_version.py
hydrilla/builder/build.py
hydrilla/builder/locales/en_US/LC_MESSAGES/hydrilla-messages.mo
hydrilla/builder/locales/en_US/LC_MESSAGES/hydrilla-messages.po
hydrilla/schemas/api_mapping_description-1.0.1.schema.json
hydrilla/schemas/api_mapping_description-1.0.1.schema.json.license
hydrilla/schemas/api_query_result-1.0.1.schema.json
hydrilla/schemas/api_query_result-1.0.1.schema.json.license
hydrilla/schemas/api_resource_description-1.0.1.schema.json
hydrilla/schemas/api_resource_description-1.0.1.schema.json.license
hydrilla/schemas/api_source_description-1.0.1.schema.json
hydrilla/schemas/api_source_description-1.0.1.schema.json.license
hydrilla/schemas/common_definitions-1.0.1.schema.json
hydrilla/schemas/common_definitions-1.0.1.schema.json.license
hydrilla/schemas/package_source-1.0.1.schema.json
hydrilla/schemas/package_source-1.0.1.schema.json.license
hydrilla/util/__init__.py
hydrilla/util/_util.py
hydrilla.builder-1.0.dist-info/METADATA
hydrilla.builder-1.0.dist-info/WHEEL
hydrilla.builder-1.0.dist-info/entry_points.txt
hydrilla.builder-1.0.dist-info/top_level.txt
hydrilla.builder-1.0.dist-info/RECORD
