Metadata-Version: 2.1
Name: hydrilla.builder
Version: 1.0
Summary: Hydrilla package builder
Home-page: https://git.koszko.org/hydrilla-builder
Author: Wojtek Kosior
Author-email: koszko@koszko.org
License: AGPL-3.0-or-later
Project-URL: Bug Tracker, https://hydrillabugs.koszko.org/projects/hydrilla
Keywords: hydrilla,haketilo
Platform: UNKNOWN
Classifier: Development Status :: 4 - Beta
Classifier: Intended Audience :: Developers
Classifier: Environment :: Console
Classifier: License :: OSI Approved :: GNU Affero General Public License v3 or later (AGPLv3+)
Classifier: Natural Language :: English
Classifier: Operating System :: OS Independent
Classifier: Programming Language :: Python :: 3 :: Only
Classifier: Topic :: Software Development :: Build Tools
Requires-Python: >=3.7
Requires-Dist: click
Requires-Dist: jsonschema (>=3.0)
Provides-Extra: setup
Requires-Dist: setuptools-scm ; extra == 'setup'
Provides-Extra: test
Requires-Dist: pytest ; extra == 'test'
